GEOpurify/GEOpurify.py
GEOpurify/__init__.py
GEOpurify-0.1.dist-info/DESCRIPTION.rst
GEOpurify-0.1.dist-info/METADATA
GEOpurify-0.1.dist-info/RECORD
GEOpurify-0.1.dist-info/WHEEL
GEOpurify-0.1.dist-info/metadata.json
GEOpurify-0.1.dist-info/top_level.txt
