Metadata-Version: 2.0
Name: GEOpurify
Version: 0.1
Summary: Making Gene Expression Omnibus data cleansing easy.
Home-page: https://github.com/biologos/GEOpurify
Author: Sasha Illarionov
Author-email: sasha.delly@gmail.com
License: MIT
Download-URL: https://github.com/biologos/GEOpurify/archive/0.1.tar.gz
Keywords: GEO,bioinformatics
Platform: UNKNOWN
Classifier: Development Status :: 3 - Alpha
Classifier: Intended Audience :: Science/Research
Classifier: License :: OSI Approved :: MIT License
Classifier: Natural Language :: English
Classifier: Programming Language :: Python :: 3.5
Classifier: Programming Language :: Python :: 3.6
Requires-Dist: GEOparse
Requires-Dist: pandas
